cythoncolortools/README.MD
cythoncolortools/__init__.py
cythoncolortools/pictcycomp.pyx
cythoncolortools/requirements.txt
cythoncolortools/thirdparty.json
cythoncolortools-0.11.dist-info/LICENSE.rst
cythoncolortools-0.11.dist-info/METADATA
cythoncolortools-0.11.dist-info/WHEEL
cythoncolortools-0.11.dist-info/top_level.txt
cythoncolortools-0.11.dist-info/RECORD
