Metadata-Version: 2.1
Name: cythoncolortools
Version: 0.11
Summary: Checks if colors are in image / Detects multiple colors in images - Fast Cython algorithm
Home-page: https://github.com/hansalemaos/cythoncolortools
Author: Johannes Fischer
Author-email: aulasparticularesdealemaosp@gmail.com
License: MIT
Keywords: colors
Classifier: Development Status :: 4 - Beta
Classifier: Programming Language :: Python :: 3 :: Only
Classifier: Programming Language :: Python :: 3.10
Classifier: Topic :: Software Development :: Libraries :: Python Modules
Classifier: Topic :: Utilities
License-File: LICENSE.rst
Requires-Dist: cycompi
Requires-Dist: numpy
